{
  "note": "Actual 2026 MLB Draft first-round order (post Dec 9, 2025 lottery), including PPI/penalty picks and Competitive Balance Round A.",
  "source": "MLB.com draft order + 2026 MLB Draft (Wikipedia)",
  "order": [
    {
      "pick": 1,
      "team": "Chicago White Sox",
      "note": "won the 2026 draft lottery"
    },
    {
      "pick": 2,
      "team": "Tampa Bay Rays",
      "note": ""
    },
    {
      "pick": 3,
      "team": "Minnesota Twins",
      "note": ""
    },
    {
      "pick": 4,
      "team": "San Francisco Giants",
      "note": ""
    },
    {
      "pick": 5,
      "team": "Pittsburgh Pirates",
      "note": ""
    },
    {
      "pick": 6,
      "team": "Kansas City Royals",
      "note": ""
    },
    {
      "pick": 7,
      "team": "Baltimore Orioles",
      "note": ""
    },
    {
      "pick": 8,
      "team": "Athletics",
      "note": ""
    },
    {
      "pick": 9,
      "team": "Atlanta Braves",
      "note": ""
    },
    {
      "pick": 10,
      "team": "Colorado Rockies",
      "note": ""
    },
    {
      "pick": 11,
      "team": "Washington Nationals",
      "note": ""
    },
    {
      "pick": 12,
      "team": "Los Angeles Angels",
      "note": ""
    },
    {
      "pick": 13,
      "team": "St. Louis Cardinals",
      "note": ""
    },
    {
      "pick": 14,
      "team": "Miami Marlins",
      "note": ""
    },
    {
      "pick": 15,
      "team": "Arizona Diamondbacks",
      "note": ""
    },
    {
      "pick": 16,
      "team": "Texas Rangers",
      "note": ""
    },
    {
      "pick": 17,
      "team": "Houston Astros",
      "note": ""
    },
    {
      "pick": 18,
      "team": "Cincinnati Reds",
      "note": ""
    },
    {
      "pick": 19,
      "team": "Cleveland Guardians",
      "note": ""
    },
    {
      "pick": 20,
      "team": "Boston Red Sox",
      "note": ""
    },
    {
      "pick": 21,
      "team": "San Diego Padres",
      "note": ""
    },
    {
      "pick": 22,
      "team": "Detroit Tigers",
      "note": ""
    },
    {
      "pick": 23,
      "team": "Chicago Cubs",
      "note": ""
    },
    {
      "pick": 24,
      "team": "Seattle Mariners",
      "note": ""
    },
    {
      "pick": 25,
      "team": "Milwaukee Brewers",
      "note": ""
    },
    {
      "pick": 26,
      "team": "Atlanta Braves",
      "note": "Prospect Promotion Incentive (Drake Baldwin, NL ROY)"
    },
    {
      "pick": 27,
      "team": "New York Mets",
      "note": "moved back for exceeding the top CBT threshold"
    },
    {
      "pick": 28,
      "team": "Houston Astros",
      "note": "Prospect Promotion Incentive (Hunter Brown, top-3 Cy Young)"
    },
    {
      "pick": 29,
      "team": "San Francisco Giants",
      "note": "Competitive Balance Round A (acquired from Cleveland)"
    },
    {
      "pick": 30,
      "team": "Kansas City Royals",
      "note": "Competitive Balance Round A"
    },
    {
      "pick": 31,
      "team": "Arizona Diamondbacks",
      "note": "Competitive Balance Round A"
    },
    {
      "pick": 32,
      "team": "St. Louis Cardinals",
      "note": "Competitive Balance Round A"
    },
    {
      "pick": 33,
      "team": "Tampa Bay Rays",
      "note": "Competitive Balance Round A (acquired from Baltimore)"
    },
    {
      "pick": 34,
      "team": "Pittsburgh Pirates",
      "note": "Competitive Balance Round A"
    },
    {
      "pick": 35,
      "team": "New York Yankees",
      "note": "moved back for exceeding the top CBT threshold"
    },
    {
      "pick": 36,
      "team": "Philadelphia Phillies",
      "note": "moved back for exceeding the top CBT threshold"
    },
    {
      "pick": 37,
      "team": "Colorado Rockies",
      "note": "Competitive Balance Round A"
    }
  ]
}